sphinx_plover.py
sphinx_plover-0.3.dist-info/METADATA
sphinx_plover-0.3.dist-info/WHEEL
sphinx_plover-0.3.dist-info/top_level.txt
sphinx_plover-0.3.dist-info/zip-safe
sphinx_plover-0.3.dist-info/RECORD
