Metadata-Version: 2.1
Name: sphinx_plover
Version: 0.3
Summary: Plover domain for Sphinx
Home-page: https://github.com/sammdot/sphinx-plover
Requires-Python: >=3.8
